sevn/__init__.py
sevn/cli/__init__.py
sevn/cli/commands.py
sevn/cli/main.py
sevn/core/__init__.py
sevn/core/crypto.py
sevn/core/profiles.py
sevn-1.0.3.dist-info/LICENSE
sevn-1.0.3.dist-info/METADATA
sevn-1.0.3.dist-info/WHEEL
sevn-1.0.3.dist-info/entry_points.txt
sevn-1.0.3.dist-info/top_level.txt
sevn-1.0.3.dist-info/RECORD
